everyworld/__init__.py
everyworld/code.py
everyworld-0.0b1.dist-info/LICENSE
everyworld-0.0b1.dist-info/METADATA
everyworld-0.0b1.dist-info/WHEEL
everyworld-0.0b1.dist-info/top_level.txt
everyworld-0.0b1.dist-info/RECORD
