Metadata-Version: 2.1
Name: everyworld
Version: 0.0b1
Summary: Collection of popular libraries and useful code
Home-page: https://github.com/alexbronikitin/everyworld
Author: AlexBroNikitin
Author-email: alexnikitin071209@gmail.com
License: UNKNOWN
Project-URL: Bug Tracker, https://github.com/alexbronikitin/everyworld/issues
Platform: UNKNOWN
Classifier: Programming Language :: Python :: 3
Classifier: License :: OSI Approved :: MIT License
Classifier: Operating System :: OS Independent
Requires-Python: >=3.6
